MANIFEST.in
README.md
macaddresslink.py
setup.py
macaddresslink.egg-info/PKG-INFO
macaddresslink.egg-info/SOURCES.txt
macaddresslink.egg-info/dependency_links.txt
macaddresslink.egg-info/entry_points.txt
macaddresslink.egg-info/requires.txt
macaddresslink.egg-info/top_level.txt