Metadata-Version: 1.1
Name: macaddresslink
Version: 0.0.1
Summary: macaddress.link client
Home-page: https://github.com/MacAddressLink/macaddresslink.py
Author: Shane R. Spencer
Author-email: shane@bogomip.com
License: MIT
Platform: UNKNOWN
Classifier: Development Status :: 4 - Beta
Classifier: Intended Audience :: Developers
Classifier: License :: OSI Approved :: MIT License
Classifier: Programming Language :: Python :: Implementation :: PyPy
Classifier: Programming Language :: Python :: Implementation :: CPython
Classifier: Programming Language :: Python :: 2.6
Classifier: Programming Language :: Python :: 2.7
Classifier: Programming Language :: Python :: 3.2
Classifier: Programming Language :: Python :: 3.3
